aiofm/__init__.py
aiofm/helpers.py
aiofm/manager.py
aiofm/tst.py
aiofm/protocols/__init__.py
aiofm/protocols/memory.py
aiofm/protocols/s3.py
aiofm-0.1.4.dist-info/AUTHORS.rst
aiofm-0.1.4.dist-info/LICENSE
aiofm-0.1.4.dist-info/LICENSE.txt
aiofm-0.1.4.dist-info/METADATA
aiofm-0.1.4.dist-info/WHEEL
aiofm-0.1.4.dist-info/top_level.txt
aiofm-0.1.4.dist-info/RECORD
