Metadata-Version: 2.1
Name: aiofm
Version: 0.1.4
Summary: Async file manager for Python
Home-page: https://github.com/kamikaze/aiofm
Author: Oleg Korsak
Author-email: kamikaze.is.waiting.you@gmail.com
License: gpl3
Project-URL: Documentation, https://github.com/kamikaze/aiofm/wiki
Platform: any
Classifier: Development Status :: 4 - Beta
Classifier: Programming Language :: Python
Requires-Python: >=3.12
License-File: LICENSE
License-File: LICENSE.txt
License-File: AUTHORS.rst
Requires-Dist: aiobotocore ==2.11.0
Requires-Dist: aiohttp ==3.9.1
Requires-Dist: minio ==7.2.3
Requires-Dist: pydantic ==2.5.3
Requires-Dist: types-aiobotocore[s3] ==2.11.0
Provides-Extra: testing
Requires-Dist: pytest ; extra == 'testing'
Requires-Dist: pytest-asyncio ; extra == 'testing'
Requires-Dist: pytest-cov ; extra == 'testing'
Requires-Dist: pytest-mock ; extra == 'testing'
